sigima/__init__.py
sigima/config.py
sigima/enums.py
sigima/params.py
sigima/worker.py
sigima/client/__init__.py
sigima/client/base.py
sigima/client/remote.py
sigima/client/stub.py
sigima/client/utils.py
sigima/data/logo/Sigima.svg
sigima/data/tests/annotations.json
sigima/data/tests/fabry-perot1.jpg
sigima/data/tests/fabry-perot2.jpg
sigima/data/tests/flower.npy
sigima/data/tests/curve_fitting/exponential_fit.txt
sigima/data/tests/curve_fitting/gaussian_fit.txt
sigima/data/tests/curve_fitting/piecewiseexponential_fit.txt
sigima/data/tests/curve_fitting/polynomial_fit.txt
sigima/data/tests/curve_fitting/twohalfgaussian_fit.txt
sigima/data/tests/curve_formats/bandwidth.txt
sigima/data/tests/curve_formats/boxcar.npy
sigima/data/tests/curve_formats/datetime.txt
sigima/data/tests/curve_formats/dynamic_parameters.txt
sigima/data/tests/curve_formats/fw1e2.txt
sigima/data/tests/curve_formats/fwhm.txt
sigima/data/tests/curve_formats/multiple_curves.csv
sigima/data/tests/curve_formats/noised_saw.mat
sigima/data/tests/curve_formats/oscilloscope.csv
sigima/data/tests/curve_formats/paracetamol.npy
sigima/data/tests/curve_formats/paracetamol.txt
sigima/data/tests/curve_formats/paracetamol_dx_dy.csv
sigima/data/tests/curve_formats/paracetamol_dy.csv
sigima/data/tests/curve_formats/pulse1.npy
sigima/data/tests/curve_formats/pulse2.npy
sigima/data/tests/curve_formats/simple.txt
sigima/data/tests/curve_formats/spectrum.mca
sigima/data/tests/curve_formats/square2.npy
sigima/data/tests/curve_formats/step.npy
sigima/data/tests/curve_formats/other/recursive1.txt
sigima/data/tests/curve_formats/other/other2/recursive2.txt
sigima/data/tests/image_formats/NF 180338201.scor-data
sigima/data/tests/image_formats/binary_image.npy
sigima/data/tests/image_formats/binary_image.png
sigima/data/tests/image_formats/centroid_test.npy
sigima/data/tests/image_formats/fiber.csv
sigima/data/tests/image_formats/fiber.jpg
sigima/data/tests/image_formats/fiber.png
sigima/data/tests/image_formats/fiber.txt
sigima-1.0.6.dist-info/licenses/LICENSE
sigima-1.0.6.dist-info/METADATA
sigima-1.0.6.dist-info/WHEEL
sigima-1.0.6.dist-info/top_level.txt
sigima-1.0.6.dist-info/RECORD
