Metadata-Version: 2.4
Name: sigima
Version: 1.0.6
Summary: Scientific computing engine for 1D signals and 2D images, part of the DataLab open-source platform.
Author-email: Pierre Raybaut <p.raybaut@codra.fr>
Maintainer-email: DataLab Platform Developers <p.raybaut@codra.fr>
License: BSD 3-Clause License
Project-URL: Homepage, https://github.com/DataLab-Platform/Sigima
Project-URL: Documentation, https://sigima.readthedocs.io/
Classifier: Development Status :: 4 - Beta
Classifier: Intended Audience :: Developers
Classifier: Intended Audience :: Education
Classifier: Intended Audience :: Science/Research
Classifier: Intended Audience :: End Users/Desktop
Classifier: Operating System :: MacOS :: MacOS X
Classifier: Operating System :: Microsoft :: Windows :: Windows 7
Classifier: Operating System :: Microsoft :: Windows :: Windows 8
Classifier: Operating System :: Microsoft :: Windows :: Windows 10
Classifier: Operating System :: Microsoft :: Windows :: Windows 11
Classifier: Operating System :: POSIX :: Linux
Classifier: Programming Language :: Python :: 3.9
Classifier: Programming Language :: Python :: 3.10
Classifier: Programming Language :: Python :: 3.11
Classifier: Programming Language :: Python :: 3.12
Classifier: Programming Language :: Python :: 3.13
Classifier: Topic :: Scientific/Engineering
Classifier: Topic :: Scientific/Engineering :: Image Processing
Classifier: Topic :: Software Development :: Libraries :: Python Modules
Requires-Python: <4,>=3.9
License-File: LICENSE
Requires-Dist: guidata>=3.13
Requires-Dist: NumPy<2.5,>=1.22
Requires-Dist: SciPy<1.17,>=1.10.1
Requires-Dist: scikit-image<0.27,>=0.19.2
Requires-Dist: pandas<3.0,>=1.4
Requires-Dist: PyWavelets<2.0,>=1.2
Requires-Dist: packaging>=21.3
Requires-Dist: typing-extensions>=4.0
Requires-Dist: makefun>=1.13.1
Provides-Extra: opencv
Requires-Dist: opencv-python-headless>=4.8.1.78; extra == "opencv"
Provides-Extra: dev
Requires-Dist: build; extra == "dev"
Requires-Dist: babel; extra == "dev"
Requires-Dist: ruff; extra == "dev"
Requires-Dist: pylint; extra == "dev"
Requires-Dist: Coverage; extra == "dev"
Requires-Dist: pre-commit; extra == "dev"
Provides-Extra: doc
Requires-Dist: sphinx; extra == "doc"
Requires-Dist: sphinx-gallery; extra == "doc"
Requires-Dist: sphinx_intl; extra == "doc"
Requires-Dist: myst_parser; extra == "doc"
Requires-Dist: sphinx_design; extra == "doc"
Requires-Dist: sphinx-copybutton; extra == "doc"
Requires-Dist: pydata-sphinx-theme; extra == "doc"
Requires-Dist: qtpy; extra == "doc"
Requires-Dist: PyQt5; extra == "doc"
Requires-Dist: plotpy; extra == "doc"
Requires-Dist: opencv-python-headless>=4.8.1.78; extra == "doc"
Provides-Extra: test
Requires-Dist: pytest; extra == "test"
Requires-Dist: pytest-xvfb; extra == "test"
Provides-Extra: qt
Requires-Dist: qtpy; extra == "qt"
Requires-Dist: PyQt5; extra == "qt"
Requires-Dist: plotpy; extra == "qt"
Dynamic: license-file
